fte/__init__.py
fte/_version.txt
fte/bit_ops.py
fte/cDFA.cc
fte/cDFA_py.py
fte/conf.py
fte/dfa.py
fte/encoder.py
fte/encrypter.py
fte/rank_unrank.cc
fte/rank_unrank.h
fte/tests/__init__.py
fte/tests/test_bit_ops.py
fte/tests/test_encoder.py
fte/tests/test_encrypter.py
fte-0.2.1.dist-info/licenses/LICENSE
fte-0.2.1.dist-info/METADATA
fte-0.2.1.dist-info/WHEEL
fte-0.2.1.dist-info/top_level.txt
fte-0.2.1.dist-info/RECORD
