Metadata-Version: 2.4
Name: fte
Version: 0.2.1
Summary: Format-Transforming Encryption
Home-page: https://github.com/kpdyer/libfte
Author: Kevin P. Dyer
Author-email: "Kevin P. Dyer" <kpdyer@gmail.com>
License: MIT
Project-URL: Homepage, https://github.com/kpdyer/libfte
Project-URL: Repository, https://github.com/kpdyer/libfte
Project-URL: Documentation, https://github.com/kpdyer/libfte#readme
Keywords: cryptography,encryption,regex,DFA,FTE
Classifier: Development Status :: 4 - Beta
Classifier: Intended Audience :: Developers
Classifier: Intended Audience :: Science/Research
Classifier: License :: OSI Approved :: MIT License
Classifier: Operating System :: OS Independent
Classifier: Programming Language :: Python :: 3
Classifier: Programming Language :: Python :: 3.8
Classifier: Programming Language :: Python :: 3.9
Classifier: Programming Language :: Python :: 3.10
Classifier: Programming Language :: Python :: 3.11
Classifier: Programming Language :: Python :: 3.12
Classifier: Programming Language :: C++
Classifier: Topic :: Security :: Cryptography
Requires-Python: >=3.8
License-File: LICENSE
Requires-Dist: pycryptodome>=3.9.0
Requires-Dist: regex2dfa>=0.2.0
Provides-Extra: dev
Requires-Dist: pytest>=7.0; extra == "dev"
Requires-Dist: pytest-cov; extra == "dev"
Dynamic: author
Dynamic: home-page
Dynamic: license-file
Dynamic: requires-python
